optidata/__init__.py
optidata/core/__init__.py
optidata/core/src/__init__.py
optidata/core/src/config/__init__.py
optidata/core/src/config/api_rest.py
optidata/core/src/config/config_params.py
optidata/core/src/config/constantes.py
optidata/core/src/config/error_handling.py
optidata/core/src/config/kafka_config.py
optidata/core/src/config/settings.py
optidata/core/src/config/sftp.py
optidata/core/src/database/__init__.py
optidata/core/src/database/databases.py
optidata/core/src/database/mongo_collections.py
optidata/core/src/database/mongo_settings.py
optidata/core/src/database/mongodb.py
optidata/core/src/database/oracle.py
optidata/core/src/enums/__init__.py
optidata/core/src/enums/enums.py
optidata/core/src/log/__init__.py
optidata/core/src/log/auditory.py
optidata/core/src/log/logger.py
optidata/core/src/messages/__init__.py
optidata/core/src/messages/messages.py
optidata/core/src/services/__init__.py
optidata/core/src/services/action.py
optidata/core/src/services/action_role_relation.py
optidata/core/src/services/conciliation.py
optidata/core/src/services/config_params.py
optidata/core/src/services/config_rules.py
optidata/core/src/services/cycles.py
optidata/core/src/services/messages.py
optidata/core/src/services/partner.py
optidata/core/src/services/role.py
optidata/core/src/services/type_cycles.py
optidata/core/src/services/users.py
optidata/core/src/utility/__init__.py
optidata/core/src/utility/utils.py
optidata/core/src/utility/utils_file.py
optidata/core/src/utility/utils_messages.py
optidata_core-2.0.0.dist-info/LICENSE
optidata_core-2.0.0.dist-info/METADATA
optidata_core-2.0.0.dist-info/WHEEL
optidata_core-2.0.0.dist-info/top_level.txt
optidata_core-2.0.0.dist-info/RECORD
