Metadata-Version: 2.1
Name: optidata-core
Version: 2.0.0
Summary: Paquete de Python para OptiData
Author: Gonzalo Torres Moya
Author-email: Gonzalo Torres Moya <gtorres@optimisa.cl>
License: Copyright (c) 2018 The Python Packaging Authority
Keywords: python,optidata-core
Classifier: Programming Language :: Python :: 3
Classifier: License :: OSI Approved :: MIT License
Classifier: Operating System :: OS Independent
Requires-Python: >=3.9
License-File: LICENSE
Requires-Dist: flask ==3.0.3
Requires-Dist: Flask-Bcrypt ==1.0.1
Requires-Dist: Flask-JWT-Extended ==4.6.0
Requires-Dist: Flask-Compress ==1.15
Requires-Dist: Flask-Cors ==4.0.1
Requires-Dist: flask-restx ==1.3.0
Requires-Dist: numpy ==1.26.4
Requires-Dist: openpyxl ==3.1.5
Requires-Dist: pandas ==2.1.0
Requires-Dist: pymongo ==4.8.0
Requires-Dist: pysftp ==0.2.9
Requires-Dist: vaex ==4.17.0
Requires-Dist: pydantic-settings ==2.4.0
Requires-Dist: kafka-python ==2.0.2
Requires-Dist: joblib ==1.4.2
Requires-Dist: paramiko ==3.4.1
Requires-Dist: oracledb ==2.4.1
Requires-Dist: SQLAlchemy ==2.0.32
Requires-Dist: APScheduler ==4.0.0a5
Requires-Dist: Fernet ==1.0.1
Requires-Dist: retrying ==1.3.4
Requires-Dist: pycryptodome ==3.20.0
Requires-Dist: cryptography ==43.0.0
Requires-Dist: werkzeug ==3.0.4
Requires-Dist: setuptools ==73.0.1
Requires-Dist: chardet ==5.2.0
Requires-Dist: bcrypt ==4.2.0
Requires-Dist: anyio ==4.4.0
Requires-Dist: pillow ==10.4.0
Requires-Dist: pydantic ==2.8.2
Requires-Dist: Paste ==3.10.1
